{
  "generatedAt": "2026-06-15T08:31:11.326Z",
  "numSimulations": 20000,
  "methodology": {
    "ratingSource": "Ratings are computed deterministically from a frozen pre-tournament Elo snapshot (elo_baseline.json, fetched 2026-06-11) plus every played result in results.json, applied in date order via the standard World Cup Elo formula (K=60, goal-difference weighted), with each in-tournament result's rating change multiplied by 1.5x (on the basis that current tournament form is more representative of a team's true strength than their pre-tournament rating alone). No live fetch is used, so there is no possibility of double-counting against eloratings.net's own updates. Run scripts/sim/compareToLive.js periodically to check this against live eloratings.net values (noting ours will diverge somewhat by design, due to the multiplier).",
    "fifaRank": "fifaRank is the official FIFA/Coca-Cola Men's World Ranking position (1-211ish across all FIFA members; only the 48 World Cup teams are listed here), from the 11 June 2026 update - the last one before the tournament (next update: 20 July 2026, after the tournament). This is FIFA's own ranking, independent of and not used by this site's model - included for comparison only. See scripts/fifaRankings.js.",
    "eloRatings": "eloBaseline is each team's rating immediately before the tournament (elo_baseline.json). eloRating is their CURRENT rating, adjusted for tournament performance so far (see ratingSource above). eloChange = eloRating - eloBaseline.",
    "homeAdvantage": 100,
    "drawModel": "empirical (base 26% at parity, floor 12% for large gaps)",
    "thirdPlaceAndBracket": "simplified approximation of FIFA Annex C; not the official 495-scenario mapping",
    "knockoutTies": "extra time/penalties treated as draw-probability mass resolved ~50/50 with a small Elo-based tilt",
    "liveResults": "8 completed group-stage result(s) as of 2026-06-13 are applied directly (not simulated) in every simulation run, and have updated each involved team's Elo rating (eloRating below) using the standard World Cup Elo formula (K=60, goal-difference weighted).",
    "climateAdjustment": "group-stage matches include a small Elo-equivalent adjustment (+/-25 points, see scripts/sim/venues.js) based on each team's acclimatisation to that group's representative host-city altitude/heat profile. Directional, not a fitted parameter. Not applied to knockout matches."
  },
  "teams": [
    {
      "name": "Spain",
      "code": "ES",
      "group": "H",
      "fifaRank": 2,
      "eloBaseline": 2157,
      "eloRating": 2157,
      "eloChange": 0,
      "pGroupWinner": 0.8346,
      "pRunnerUp": 0.15645,
      "pRoundOf32": 0.99805,
      "pRoundOf16": 0.81305,
      "pQuarterFinal": 0.62325,
      "pSemiFinal": 0.40125,
      "pFinal": 0.3086,
      "pChampion": 0.1959
    },
    {
      "name": "Argentina",
      "code": "AR",
      "group": "J",
      "fifaRank": 3,
      "eloBaseline": 2115,
      "eloRating": 2115,
      "eloChange": 0,
      "pGroupWinner": 0.84125,
      "pRunnerUp": 0.1292,
      "pRoundOf32": 0.99385,
      "pRoundOf16": 0.7204,
      "pQuarterFinal": 0.5208,
      "pSemiFinal": 0.3537,
      "pFinal": 0.24815,
      "pChampion": 0.16205
    },
    {
      "name": "France",
      "code": "FR",
      "group": "I",
      "fifaRank": 1,
      "eloBaseline": 2063,
      "eloRating": 2063,
      "eloChange": 0,
      "pGroupWinner": 0.65555,
      "pRunnerUp": 0.2505,
      "pRoundOf32": 0.98295,
      "pRoundOf16": 0.77385,
      "pQuarterFinal": 0.56005,
      "pSemiFinal": 0.3625,
      "pFinal": 0.18025,
      "pChampion": 0.10055
    },
    {
      "name": "England",
      "code": "EN",
      "group": "L",
      "fifaRank": 4,
      "eloBaseline": 2024,
      "eloRating": 2024,
      "eloChange": 0,
      "pGroupWinner": 0.6486,
      "pRunnerUp": 0.282,
      "pRoundOf32": 0.9876,
      "pRoundOf16": 0.7236,
      "pQuarterFinal": 0.4178,
      "pSemiFinal": 0.2599,
      "pFinal": 0.1324,
      "pChampion": 0.068
    },
    {
      "name": "USA",
      "code": "US",
      "group": "D",
      "fifaRank": 16,
      "eloBaseline": 1780,
      "eloRating": 1836.6897625310455,
      "eloChange": 56.68976253104552,
      "pGroupWinner": 0.6403,
      "pRunnerUp": 0.2762,
      "pRoundOf32": 0.9949,
      "pRoundOf16": 0.70355,
      "pQuarterFinal": 0.4506,
      "pSemiFinal": 0.28345,
      "pFinal": 0.15015,
      "pChampion": 0.06755
    },
    {
      "name": "Portugal",
      "code": "PT",
      "group": "K",
      "fifaRank": 5,
      "eloBaseline": 1989,
      "eloRating": 1989,
      "eloChange": 0,
      "pGroupWinner": 0.4974,
      "pRunnerUp": 0.3965,
      "pRoundOf32": 0.9667,
      "pRoundOf16": 0.6537,
      "pQuarterFinal": 0.3849,
      "pSemiFinal": 0.19575,
      "pFinal": 0.10895,
      "pChampion": 0.05175
    },
    {
      "name": "Mexico",
      "code": "MX",
      "group": "A",
      "fifaRank": 15,
      "eloBaseline": 1881,
      "eloRating": 1889.4573978462747,
      "eloChange": 8.457397846274716,
      "pGroupWinner": 0.80865,
      "pRunnerUp": 0.18075,
      "pRoundOf32": 0.99985,
      "pRoundOf16": 0.7441,
      "pQuarterFinal": 0.4154,
      "pSemiFinal": 0.1849,
      "pFinal": 0.08745,
      "pChampion": 0.0482
    },
    {
      "name": "Colombia",
      "code": "CO",
      "group": "K",
      "fifaRank": 13,
      "eloBaseline": 1982,
      "eloRating": 1982,
      "eloChange": 0,
      "pGroupWinner": 0.4604,
      "pRunnerUp": 0.41725,
      "pRoundOf32": 0.963,
      "pRoundOf16": 0.6378,
      "pQuarterFinal": 0.3614,
      "pSemiFinal": 0.18455,
      "pFinal": 0.09815,
      "pChampion": 0.04555
    },
    {
      "name": "Brazil",
      "code": "BR",
      "group": "C",
      "fifaRank": 6,
      "eloBaseline": 1991,
      "eloRating": 1971.2072894647563,
      "eloChange": -19.792710535243714,
      "pGroupWinner": 0.49895,
      "pRunnerUp": 0.3422,
      "pRoundOf32": 0.97365,
      "pRoundOf16": 0.5864,
      "pQuarterFinal": 0.3463,
      "pSemiFinal": 0.1806,
      "pFinal": 0.0773,
      "pChampion": 0.03345
    },
    {
      "name": "Canada",
      "code": "CA",
      "group": "B",
      "fifaRank": 30,
      "eloBaseline": 1767,
      "eloRating": 1739.1712802262746,
      "eloChange": -27.828719773725425,
      "pGroupWinner": 0.43995,
      "pRunnerUp": 0.3128,
      "pRoundOf32": 0.92475,
      "pRoundOf16": 0.4953,
      "pQuarterFinal": 0.18585,
      "pSemiFinal": 0.1209,
      "pFinal": 0.06065,
      "pChampion": 0.03205
    },
    {
      "name": "Netherlands",
      "code": "NL",
      "group": "F",
      "fifaRank": 7,
      "eloBaseline": 1948,
      "eloRating": 1948,
      "eloChange": 0,
      "pGroupWinner": 0.4696,
      "pRunnerUp": 0.38425,
      "pRoundOf32": 0.9497,
      "pRoundOf16": 0.5545,
      "pQuarterFinal": 0.3313,
      "pSemiFinal": 0.16135,
      "pFinal": 0.06535,
      "pChampion": 0.027
    },
    {
      "name": "Ecuador",
      "code": "EC",
      "group": "E",
      "fifaRank": 23,
      "eloBaseline": 1938,
      "eloRating": 1938,
      "eloChange": 0,
      "pGroupWinner": 0.46715,
      "pRunnerUp": 0.3864,
      "pRoundOf32": 0.9696,
      "pRoundOf16": 0.57275,
      "pQuarterFinal": 0.28035,
      "pSemiFinal": 0.1452,
      "pFinal": 0.06045,
      "pChampion": 0.02455
    },
    {
      "name": "Germany",
      "code": "DE",
      "group": "E",
      "fifaRank": 10,
      "eloBaseline": 1932,
      "eloRating": 1932,
      "eloChange": 0,
      "pGroupWinner": 0.45415,
      "pRunnerUp": 0.39315,
      "pRoundOf32": 0.9661,
      "pRoundOf16": 0.56195,
      "pQuarterFinal": 0.27595,
      "pSemiFinal": 0.14245,
      "pFinal": 0.0558,
      "pChampion": 0.0227
    },
    {
      "name": "Japan",
      "code": "JP",
      "group": "F",
      "fifaRank": 18,
      "eloBaseline": 1906,
      "eloRating": 1906,
      "eloChange": 0,
      "pGroupWinner": 0.46195,
      "pRunnerUp": 0.3829,
      "pRoundOf32": 0.94615,
      "pRoundOf16": 0.49065,
      "pQuarterFinal": 0.2661,
      "pSemiFinal": 0.11705,
      "pFinal": 0.0452,
      "pChampion": 0.0165
    },
    {
      "name": "Norway",
      "code": "NO",
      "group": "I",
      "fifaRank": 31,
      "eloBaseline": 1914,
      "eloRating": 1914,
      "eloChange": 0,
      "pGroupWinner": 0.2127,
      "pRunnerUp": 0.41085,
      "pRoundOf32": 0.86635,
      "pRoundOf16": 0.4856,
      "pQuarterFinal": 0.24685,
      "pSemiFinal": 0.1173,
      "pFinal": 0.04395,
      "pChampion": 0.0162
    },
    {
      "name": "Croatia",
      "code": "HR",
      "group": "L",
      "fifaRank": 11,
      "eloBaseline": 1912,
      "eloRating": 1912,
      "eloChange": 0,
      "pGroupWinner": 0.3005,
      "pRunnerUp": 0.50055,
      "pRoundOf32": 0.94705,
      "pRoundOf16": 0.499,
      "pQuarterFinal": 0.2022,
      "pSemiFinal": 0.09845,
      "pFinal": 0.0426,
      "pChampion": 0.0154
    },
    {
      "name": "Belgium",
      "code": "BE",
      "group": "G",
      "fifaRank": 9,
      "eloBaseline": 1894,
      "eloRating": 1894,
      "eloChange": 0,
      "pGroupWinner": 0.62605,
      "pRunnerUp": 0.25855,
      "pRoundOf32": 0.96795,
      "pRoundOf16": 0.6483,
      "pQuarterFinal": 0.3006,
      "pSemiFinal": 0.09455,
      "pFinal": 0.0394,
      "pChampion": 0.01335
    },
    {
      "name": "Australia",
      "code": "AU",
      "group": "D",
      "fifaRank": 27,
      "eloBaseline": 1777,
      "eloRating": 1869.3152024161438,
      "eloChange": 92.31520241614385,
      "pGroupWinner": 0.3429,
      "pRunnerUp": 0.55545,
      "pRoundOf32": 0.9857,
      "pRoundOf16": 0.6084,
      "pQuarterFinal": 0.23785,
      "pSemiFinal": 0.07845,
      "pFinal": 0.0299,
      "pChampion": 0.0105
    },
    {
      "name": "Uruguay",
      "code": "UY",
      "group": "H",
      "fifaRank": 17,
      "eloBaseline": 1892,
      "eloRating": 1892,
      "eloChange": 0,
      "pGroupWinner": 0.15865,
      "pRunnerUp": 0.6949,
      "pRoundOf32": 0.94215,
      "pRoundOf16": 0.326,
      "pQuarterFinal": 0.1709,
      "pSemiFinal": 0.07825,
      "pFinal": 0.0325,
      "pChampion": 0.0101
    },
    {
      "name": "Senegal",
      "code": "SN",
      "group": "I",
      "fifaRank": 14,
      "eloBaseline": 1860,
      "eloRating": 1860,
      "eloChange": 0,
      "pGroupWinner": 0.12925,
      "pRunnerUp": 0.30845,
      "pRoundOf32": 0.77075,
      "pRoundOf16": 0.357,
      "pQuarterFinal": 0.1547,
      "pSemiFinal": 0.06275,
      "pFinal": 0.02215,
      "pChampion": 0.0073
    },
    {
      "name": "South Korea",
      "code": "KR",
      "group": "A",
      "fifaRank": 25,
      "eloBaseline": 1786,
      "eloRating": 1821.557838819284,
      "eloChange": 35.557838819283916,
      "pGroupWinner": 0.18815,
      "pRunnerUp": 0.75875,
      "pRoundOf32": 0.98985,
      "pRoundOf16": 0.5741,
      "pQuarterFinal": 0.2143,
      "pSemiFinal": 0.0656,
      "pFinal": 0.02135,
      "pChampion": 0.00665
    },
    {
      "name": "Switzerland",
      "code": "CH",
      "group": "B",
      "fifaRank": 19,
      "eloBaseline": 1891,
      "eloRating": 1851.6382652308498,
      "eloChange": -39.36173476915019,
      "pGroupWinner": 0.40655,
      "pRunnerUp": 0.2872,
      "pRoundOf32": 0.85195,
      "pRoundOf16": 0.4761,
      "pQuarterFinal": 0.1903,
      "pSemiFinal": 0.0589,
      "pFinal": 0.0195,
      "pChampion": 0.00655
    },
    {
      "name": "Morocco",
      "code": "MA",
      "group": "C",
      "fifaRank": 8,
      "eloBaseline": 1827,
      "eloRating": 1846.7927105352437,
      "eloChange": 19.792710535243714,
      "pGroupWinner": 0.2847,
      "pRunnerUp": 0.3621,
      "pRoundOf32": 0.9192,
      "pRoundOf16": 0.38005,
      "pQuarterFinal": 0.16385,
      "pSemiFinal": 0.06515,
      "pFinal": 0.0213,
      "pChampion": 0.00605
    },
    {
      "name": "Scotland",
      "code": "SQ",
      "group": "C",
      "fifaRank": 43,
      "eloBaseline": 1782,
      "eloRating": 1800.5723331130648,
      "eloChange": 18.572333113064815,
      "pGroupWinner": 0.21615,
      "pRunnerUp": 0.29185,
      "pRoundOf32": 0.8928,
      "pRoundOf16": 0.302,
      "pQuarterFinal": 0.1114,
      "pSemiFinal": 0.0394,
      "pFinal": 0.01035,
      "pChampion": 0.0029
    },
    {
      "name": "Austria",
      "code": "AT",
      "group": "J",
      "fifaRank": 24,
      "eloBaseline": 1830,
      "eloRating": 1830,
      "eloChange": 0,
      "pGroupWinner": 0.0812,
      "pRunnerUp": 0.3792,
      "pRoundOf32": 0.68295,
      "pRoundOf16": 0.19335,
      "pQuarterFinal": 0.07905,
      "pSemiFinal": 0.0289,
      "pFinal": 0.0093,
      "pChampion": 0.0023
    },
    {
      "name": "Turkiye",
      "code": "TR",
      "group": "D",
      "fifaRank": 22,
      "eloBaseline": 1911,
      "eloRating": 1818.6847975838562,
      "eloChange": -92.31520241614385,
      "pGroupWinner": 0.01285,
      "pRunnerUp": 0.10955,
      "pRoundOf32": 0.4493,
      "pRoundOf16": 0.16385,
      "pQuarterFinal": 0.0543,
      "pSemiFinal": 0.02065,
      "pFinal": 0.00685,
      "pChampion": 0.00185
    },
    {
      "name": "Iran",
      "code": "IR",
      "group": "G",
      "fifaRank": 21,
      "eloBaseline": 1772,
      "eloRating": 1772,
      "eloChange": 0,
      "pGroupWinner": 0.238,
      "pRunnerUp": 0.3827,
      "pRoundOf32": 0.82875,
      "pRoundOf16": 0.35035,
      "pQuarterFinal": 0.0959,
      "pSemiFinal": 0.022,
      "pFinal": 0.00455,
      "pChampion": 0.0013
    },
    {
      "name": "Algeria",
      "code": "DZ",
      "group": "J",
      "fifaRank": 28,
      "eloBaseline": 1772,
      "eloRating": 1772,
      "eloChange": 0,
      "pGroupWinner": 0.06205,
      "pRunnerUp": 0.3335,
      "pRoundOf32": 0.634,
      "pRoundOf16": 0.146,
      "pQuarterFinal": 0.0497,
      "pSemiFinal": 0.0136,
      "pFinal": 0.00355,
      "pChampion": 0.0009
    },
    {
      "name": "Ivory Coast",
      "code": "CI",
      "group": "E",
      "fifaRank": 34,
      "eloBaseline": 1695,
      "eloRating": 1695,
      "eloChange": 0,
      "pGroupWinner": 0.07825,
      "pRunnerUp": 0.20975,
      "pRoundOf32": 0.70595,
      "pRoundOf16": 0.1741,
      "pQuarterFinal": 0.0404,
      "pSemiFinal": 0.0096,
      "pFinal": 0.00235,
      "pChampion": 0.00065
    },
    {
      "name": "Egypt",
      "code": "EG",
      "group": "G",
      "fifaRank": 29,
      "eloBaseline": 1696,
      "eloRating": 1696,
      "eloChange": 0,
      "pGroupWinner": 0.1163,
      "pRunnerUp": 0.2705,
      "pRoundOf32": 0.6653,
      "pRoundOf16": 0.21265,
      "pQuarterFinal": 0.03965,
      "pSemiFinal": 0.0063,
      "pFinal": 0.0013,
      "pChampion": 0.00045
    },
    {
      "name": "Czechia",
      "code": "CZ",
      "group": "A",
      "fifaRank": 41,
      "eloBaseline": 1712,
      "eloRating": 1676.442161180716,
      "eloChange": -35.557838819283916,
      "pGroupWinner": 0.00275,
      "pRunnerUp": 0.0413,
      "pRoundOf32": 0.49995,
      "pRoundOf16": 0.14485,
      "pQuarterFinal": 0.03315,
      "pSemiFinal": 0.0049,
      "pFinal": 0.00095,
      "pChampion": 0.0004
    },
    {
      "name": "Uzbekistan",
      "code": "UZ",
      "group": "K",
      "fifaRank": 50,
      "eloBaseline": 1714,
      "eloRating": 1714,
      "eloChange": 0,
      "pGroupWinner": 0.0309,
      "pRunnerUp": 0.12395,
      "pRoundOf32": 0.4409,
      "pRoundOf16": 0.0959,
      "pQuarterFinal": 0.021,
      "pSemiFinal": 0.005,
      "pFinal": 0.0011,
      "pChampion": 0.0003
    },
    {
      "name": "Paraguay",
      "code": "PY",
      "group": "D",
      "fifaRank": 40,
      "eloBaseline": 1780,
      "eloRating": 1723.3102374689545,
      "eloChange": -56.68976253104552,
      "pGroupWinner": 0.00395,
      "pRunnerUp": 0.0588,
      "pRoundOf32": 0.19335,
      "pRoundOf16": 0.0518,
      "pQuarterFinal": 0.0117,
      "pSemiFinal": 0.003,
      "pFinal": 0.00095,
      "pChampion": 0.00025
    },
    {
      "name": "Panama",
      "code": "PA",
      "group": "L",
      "fifaRank": 33,
      "eloBaseline": 1730,
      "eloRating": 1730,
      "eloChange": 0,
      "pGroupWinner": 0.0496,
      "pRunnerUp": 0.20075,
      "pRoundOf32": 0.639,
      "pRoundOf16": 0.1507,
      "pQuarterFinal": 0.0416,
      "pSemiFinal": 0.01005,
      "pFinal": 0.00175,
      "pChampion": 0.00025
    },
    {
      "name": "Bosnia-Herzegovina",
      "code": "BA",
      "group": "B",
      "fifaRank": 65,
      "eloBaseline": 1616,
      "eloRating": 1643.8287197737254,
      "eloChange": 27.828719773725425,
      "pGroupWinner": 0.1357,
      "pRunnerUp": 0.3165,
      "pRoundOf32": 0.73255,
      "pRoundOf16": 0.17765,
      "pQuarterFinal": 0.03455,
      "pSemiFinal": 0.0047,
      "pFinal": 0.0012,
      "pChampion": 0.00015
    },
    {
      "name": "Sweden",
      "code": "SE",
      "group": "F",
      "fifaRank": 38,
      "eloBaseline": 1712,
      "eloRating": 1712,
      "eloChange": 0,
      "pGroupWinner": 0.04705,
      "pRunnerUp": 0.14065,
      "pRoundOf32": 0.4585,
      "pRoundOf16": 0.1169,
      "pQuarterFinal": 0.03065,
      "pSemiFinal": 0.0084,
      "pFinal": 0.00205,
      "pChampion": 0.0001
    },
    {
      "name": "Qatar",
      "code": "QA",
      "group": "B",
      "fifaRank": 55,
      "eloBaseline": 1421,
      "eloRating": 1460.3617347691502,
      "eloChange": 39.36173476915019,
      "pGroupWinner": 0.0178,
      "pRunnerUp": 0.0835,
      "pRoundOf32": 0.20325,
      "pRoundOf16": 0.01855,
      "pQuarterFinal": 0.0023,
      "pSemiFinal": 0.00015,
      "pFinal": 0.0001,
      "pChampion": 0.00005
    },
    {
      "name": "Tunisia",
      "code": "TN",
      "group": "F",
      "fifaRank": 44,
      "eloBaseline": 1628,
      "eloRating": 1628,
      "eloChange": 0,
      "pGroupWinner": 0.0214,
      "pRunnerUp": 0.0922,
      "pRoundOf32": 0.3109,
      "pRoundOf16": 0.0552,
      "pQuarterFinal": 0.0094,
      "pSemiFinal": 0.00215,
      "pFinal": 0.0006,
      "pChampion": 0.00005
    },
    {
      "name": "Cape Verde",
      "code": "CV",
      "group": "H",
      "fifaRank": 69,
      "eloBaseline": 1578,
      "eloRating": 1578,
      "eloChange": 0,
      "pGroupWinner": 0.0038,
      "pRunnerUp": 0.0748,
      "pRoundOf32": 0.2945,
      "pRoundOf16": 0.03715,
      "pQuarterFinal": 0.0063,
      "pSemiFinal": 0.00095,
      "pFinal": 0.00025,
      "pChampion": 0.00005
    },
    {
      "name": "Saudi Arabia",
      "code": "SA",
      "group": "H",
      "fifaRank": 61,
      "eloBaseline": 1576,
      "eloRating": 1576,
      "eloChange": 0,
      "pGroupWinner": 0.00295,
      "pRunnerUp": 0.07385,
      "pRoundOf32": 0.2935,
      "pRoundOf16": 0.03395,
      "pQuarterFinal": 0.00615,
      "pSemiFinal": 0.00095,
      "pFinal": 0.00025,
      "pChampion": 0.00005
    },
    {
      "name": "Jordan",
      "code": "JO",
      "group": "J",
      "fifaRank": 63,
      "eloBaseline": 1680,
      "eloRating": 1680,
      "eloChange": 0,
      "pGroupWinner": 0.0155,
      "pRunnerUp": 0.1581,
      "pRoundOf32": 0.33815,
      "pRoundOf16": 0.05925,
      "pQuarterFinal": 0.01375,
      "pSemiFinal": 0.00365,
      "pFinal": 0.00055,
      "pChampion": 0.00005
    },
    {
      "name": "Congo DR",
      "code": "CD",
      "group": "K",
      "fifaRank": 46,
      "eloBaseline": 1652,
      "eloRating": 1652,
      "eloChange": 0,
      "pGroupWinner": 0.0113,
      "pRunnerUp": 0.0623,
      "pRoundOf32": 0.2543,
      "pRoundOf16": 0.0387,
      "pQuarterFinal": 0.0067,
      "pSemiFinal": 0.0014,
      "pFinal": 0.0002,
      "pChampion": 0.00005
    },
    {
      "name": "South Africa",
      "code": "ZA",
      "group": "A",
      "fifaRank": 60,
      "eloBaseline": 1511,
      "eloRating": 1502.5426021537253,
      "eloChange": -8.457397846274716,
      "pGroupWinner": 0.00045,
      "pRunnerUp": 0.0192,
      "pRoundOf32": 0.10395,
      "pRoundOf16": 0.02005,
      "pQuarterFinal": 0.0019,
      "pSemiFinal": 0.00015,
      "pFinal": 0,
      "pChampion": 0
    },
    {
      "name": "Haiti",
      "code": "HT",
      "group": "C",
      "fifaRank": 83,
      "eloBaseline": 1548,
      "eloRating": 1529.4276668869352,
      "eloChange": -18.572333113064815,
      "pGroupWinner": 0.0002,
      "pRunnerUp": 0.00385,
      "pRoundOf32": 0.02795,
      "pRoundOf16": 0.00205,
      "pQuarterFinal": 0.0003,
      "pSemiFinal": 0,
      "pFinal": 0,
      "pChampion": 0
    },
    {
      "name": "Curacao",
      "code": "CW",
      "group": "E",
      "fifaRank": 82,
      "eloBaseline": 1434,
      "eloRating": 1434,
      "eloChange": 0,
      "pGroupWinner": 0.00045,
      "pRunnerUp": 0.0107,
      "pRoundOf32": 0.0616,
      "pRoundOf16": 0.0044,
      "pQuarterFinal": 0.0004,
      "pSemiFinal": 0,
      "pFinal": 0,
      "pChampion": 0
    },
    {
      "name": "New Zealand",
      "code": "NZ",
      "group": "G",
      "fifaRank": 85,
      "eloBaseline": 1562,
      "eloRating": 1562,
      "eloChange": 0,
      "pGroupWinner": 0.01965,
      "pRunnerUp": 0.08825,
      "pRoundOf32": 0.245,
      "pRoundOf16": 0.04135,
      "pQuarterFinal": 0.0039,
      "pSemiFinal": 0.0004,
      "pFinal": 0.00005,
      "pChampion": 0
    },
    {
      "name": "Iraq",
      "code": "IQ",
      "group": "I",
      "fifaRank": 57,
      "eloBaseline": 1607,
      "eloRating": 1607,
      "eloChange": 0,
      "pGroupWinner": 0.0025,
      "pRunnerUp": 0.0302,
      "pRoundOf32": 0.0993,
      "pRoundOf16": 0.0163,
      "pQuarterFinal": 0.0031,
      "pSemiFinal": 0.0005,
      "pFinal": 0.0002,
      "pChampion": 0
    },
    {
      "name": "Ghana",
      "code": "GH",
      "group": "L",
      "fifaRank": 74,
      "eloBaseline": 1510,
      "eloRating": 1510,
      "eloChange": 0,
      "pGroupWinner": 0.0013,
      "pRunnerUp": 0.0167,
      "pRoundOf32": 0.0865,
      "pRoundOf16": 0.0068,
      "pQuarterFinal": 0.00115,
      "pSemiFinal": 0.00025,
      "pFinal": 0.00005,
      "pChampion": 0
    }
  ]
}